[
  {
    "title": "CABO VERDE 0 X 0 ARÁBIA SAUDITA | MOMENTO HISTÓRICO | Giro da Rodada | Copa do Mundo 2026 | sportv",
    "videoId": "40_9VrGhIC8",
    "thumbnail": "https://i.ytimg.com/vi/40_9VrGhIC8/mqdefault.jpg"
  },
  {
    "title": "EGITO 1 X 1 IRÃ | GOL DA VITÓRIA ANULADO | Giro da Rodada | Copa do Mundo 2026 | sportv",
    "videoId": "JTnkeB9oxCg",
    "thumbnail": "https://i.ytimg.com/vi/JTnkeB9oxCg/mqdefault.jpg"
  },
  {
    "title": "URUGUAI 0 X 1 ESPANHA | FRANGO E SUBSTITUIÇÃO | Giro da Rodada | Copa do Mundo 2026 | sportv",
    "videoId": "vF33A4pKYxE",
    "thumbnail": "https://i.ytimg.com/vi/vF33A4pKYxE/mqdefault.jpg"
  },
  {
    "title": "NORUEGA 1 X 4 FRANÇA | SHOW DE DEMBÉLÉ | Giro da Rodada | Copa do Mundo 2026 | sportv",
    "videoId": "93bfwbtx9o8",
    "thumbnail": "https://i.ytimg.com/vi/93bfwbtx9o8/mqdefault.jpg"
  },
  {
    "title": "TURQUIA 3 X 2 ESTADOS UNIDOS | CONSOLAÇÃO TURCA | Giro da Rodada | Copa do Mundo 2026 | sportv",
    "videoId": "sBr4_pIrliI",
    "thumbnail": "https://i.ytimg.com/vi/sBr4_pIrliI/mqdefault.jpg"
  }
]